LICENSE
README.md
pyproject.toml
setup.py
feign_python.egg-info/PKG-INFO
feign_python.egg-info/SOURCES.txt
feign_python.egg-info/dependency_links.txt
feign_python.egg-info/top_level.txt
ldj/__init__.py
ldj/center/__init__.py
ldj/center/nacos/NacosClient.py
ldj/center/nacos/NacosIns.py
ldj/center/nacos/__init__.py
ldj/center/prop/Properties.py
ldj/center/prop/__init__.py
ldj/common/Cache.py
ldj/common/Constant.py
ldj/common/__init__.py
ldj/config/__init__.py
ldj/config/settings.py
ldj/example/DictApi.py
ldj/example/DictApi2.py
ldj/example/DictApi2NoCenter.py
ldj/example/DictApiNoCenter.py
ldj/example/ExampleConfig.py
ldj/example/TestDictApi.py
ldj/example/TestDictApi2.py
ldj/example/TestDictApi2NoCenter.py
ldj/example/TestDictApiNoCenter.py
ldj/example/TestInterceptorCall.py
ldj/example/TestNacosCall.py
ldj/example/TestStaticCall.py
ldj/example/__init__.py
ldj/example/models.py
ldj/example/dto/__init__.py
ldj/example/dto/models.py
ldj/example/interceptor/MyInterceptor.py
ldj/example/interceptor/__init__.py
ldj/feign/__init__.py
ldj/feign/center/NacosCenter.py
ldj/feign/center/RegisterCenter.py
ldj/feign/center/RegisterCenterHelper.py
ldj/feign/center/RegisterSelect.py
ldj/feign/center/__init__.py
ldj/feign/context/ServiceContext.py
ldj/feign/context/__init__.py
ldj/feign/decorator/Api.py
ldj/feign/decorator/Feign.py
ldj/feign/decorator/FeignApi.py
ldj/feign/decorator/__init__.py
ldj/feign/enums/BaseEnum.py
ldj/feign/enums/Method.py
ldj/feign/enums/RegisterCenterType.py
ldj/feign/enums/RouterType.py
ldj/feign/enums/__init__.py
ldj/feign/exception/AuthException.py
ldj/feign/exception/BusinessException.py
ldj/feign/exception/FeignException.py
ldj/feign/exception/__init__.py
ldj/feign/exception/handler/DefaultExceptionHandler.py
ldj/feign/exception/handler/ExceptionHandler.py
ldj/feign/exception/handler/__init__.py
ldj/feign/interceptor/DefaultInterceptor.py
ldj/feign/interceptor/Interceptor.py
ldj/feign/interceptor/__init__.py
ldj/feign/model/HostInfo.py
ldj/feign/model/Page.py
ldj/feign/model/Request.py
ldj/feign/model/Response.py
ldj/feign/model/ServiceInfo.py
ldj/feign/model/__init__.py
