Metadata-Version: 2.1
Name: feign-python
Version: 0.0.5
Summary: feign python实现,提供python应用与java微服务体系集成，目前支持注册中心(nacos)以及非注册中心调用模式，详情请参考源码中的example
Home-page: https://github.com/openandopen/feign-python.git
Author: ldj
Author-email: ldj <zuiwoxing@qq.com>
Project-URL: Homepage, https://github.com/openandopen/feign-python.git
Project-URL: Issues, https://github.com/openandopen/feign-python/issues
Classifier: Programming Language :: Python :: 3
Classifier: License :: OSI Approved :: MIT License
Classifier: Operating System :: OS Independent
Requires-Python: >=3.8
License-File: LICENSE
